pygem/__init__.py
pygem/bin/op/compress_gdirs.py
pygem/bin/op/duplicate_gdirs.py
pygem/bin/op/initialize.py
pygem/bin/op/list_failed_simulations.py
pygem/bin/postproc/postproc_binned_monthly_mass.py
pygem/bin/postproc/postproc_compile_simulations.py
pygem/bin/postproc/postproc_distribute_ice.py
pygem/bin/postproc/postproc_monthly_mass.py
pygem/bin/preproc/preproc_fetch_mbdata.py
pygem/bin/preproc/preproc_wgms_estimate_kp.py
pygem/bin/run/__init__.py
pygem/bin/run/run_calibration.py
pygem/bin/run/run_calibration_frontalablation.py
pygem/bin/run/run_calibration_reg_glena.py
pygem/bin/run/run_inversion.py
pygem/bin/run/run_mcmc_priors.py
pygem/bin/run/run_simulation.py
pygem/bin/run/run_spinup.py
pygem/class_climate.py
pygem/gcmbiasadj.py
pygem/glacierdynamics.py
pygem/massbalance.py
pygem/mcmc.py
pygem/oggm_compat.py
pygem/output.py
pygem/pygem_modelsetup.py
pygem/scraps/dummy_task_module.py
pygem/scraps/run.py
pygem/setup/__init__.py
pygem/setup/config.py
pygem/setup/config.yaml
pygem/shop/debris.py
pygem/shop/icethickness.py
pygem/shop/mbdata.py
pygem/shop/oib.py
pygem/tests/__init__.py
pygem/tests/test_01_basics.py
pygem/tests/test_02_config.py
pygem/tests/test_03_notebooks.py
pygem/tests/test_04_postproc.py
pygem/utils/_funcs.py
pygem/utils/_funcs_selectglaciers.py
pygem-1.0.4.dist-info/LICENSE.txt
pygem-1.0.4.dist-info/METADATA
pygem-1.0.4.dist-info/WHEEL
pygem-1.0.4.dist-info/entry_points.txt
pygem-1.0.4.dist-info/RECORD
