Metadata-Version: 2.1
Name: pygem
Version: 1.0.4
Summary: Python Glacier Evolution Model (PyGEM)
License: MIT
Author: David Rounce
Author-email: drounce@cmu.edu>,Brandon Tober <btober@cmu.edu
Requires-Python: >=3.10,<3.13
Classifier: License :: OSI Approved :: MIT License
Classifier: Programming Language :: Python :: 3
Classifier: Programming Language :: Python :: 3.10
Classifier: Programming Language :: Python :: 3.11
Classifier: Programming Language :: Python :: 3.12
Requires-Dist: PyYAML (>=6.0.2,<7.0.0)
Requires-Dist: arviz (>=0.20.0,<0.21.0)
Requires-Dist: geopandas (>=1.0.1,<2.0.0)
Requires-Dist: gpytorch (>=1.13,<2.0)
Requires-Dist: jupyter (>=1.1.1,<2.0.0)
Requires-Dist: matplotlib (>=3.9.2,<4.0.0)
Requires-Dist: nbmake (>=1.5.5)
Requires-Dist: numpy (<2.0)
Requires-Dist: oggm (>=1.6.2,<2.0.0)
Requires-Dist: pandas (>=2.2.3,<3.0.0)
Requires-Dist: pyproj (>=3.7.0,<4.0.0)
Requires-Dist: pytest (>=8.3.4)
Requires-Dist: pytest-cov (>=6.0.0)
Requires-Dist: rasterio (>=1.4.2,<2.0.0)
Requires-Dist: ruamel-yaml (>=0.18.10,<0.19.0)
Requires-Dist: ruff (>=0.9.6)
Requires-Dist: salem (>=0.3.11,<0.4.0)
Requires-Dist: scikit-learn (>=1.5.2,<2.0.0)
Requires-Dist: scipy (>=1.14.1,<2.0.0)
Requires-Dist: tables (>=3.10.1,<4.0.0)
Requires-Dist: torch (>=2.0.0,<=2.2.2)
Requires-Dist: tqdm (>=4.66.6,<5.0.0)
Requires-Dist: xarray (>=2024.10.0,<2025.0.0)
Project-URL: Documentation, https://pygem.readthedocs.io/
Project-URL: Repository, https://github.com/PyGEM-Community/PyGEM
